LICENSE
MANIFEST.in
README
setup.py
Morfessor.egg-info/PKG-INFO
Morfessor.egg-info/SOURCES.txt
Morfessor.egg-info/dependency_links.txt
Morfessor.egg-info/requires.txt
Morfessor.egg-info/top_level.txt
morfessor/__init__.py
morfessor/baseline.py
morfessor/cmd.py
morfessor/evaluation.py
morfessor/exception.py
morfessor/io.py
morfessor/utils.py
morfessor/test/__init__.py
morfessor/test/evaluation.py
scripts/morfessor
scripts/morfessor-evaluate
scripts/morfessor-segment
scripts/morfessor-train