Metadata-Version: 1.1
Name: Morfessor
Version: 2.0.0
Summary: Morfessor
Home-page: http://www.cis.hut.fi/projects/morpho/
Author: Sami Virpioja, Peter Smit
Author-email: morfessor@cis.hut.fi
License: BSD
Platform: UNKNOWN
Classifier: Development Status :: 4 - Beta
Classifier: Intended Audience :: Science/Research
Classifier: License :: OSI Approved :: BSD License
Classifier: Operating System :: OS Independent
Classifier: Programming Language :: Python
Classifier: Topic :: Scientific/Engineering
